{
    "id": 94863706,
    "name": "Yolo WILL Clear",
    "author": "Olive60",
    "creators": ["Olive60"],
    "verifier": "Olive60",
    "verification": "https://youtu.be/njGusIAPm9w",
    "percentToQualify": 35,
    "password": "No Password",
    "records": [
        {
            "user": "Yoloplex",
            "link": "",
            "percent": 100,
            "hz": 360
        },
        {
            "user": "MyRougeYoshi",
            "link": "",
            "percent": 100,
            "hz": 360
        },
        {
            "user": "and love is a prize",
            "link": "https://drive.google.com/file/d/1r5K5h9trJBqmhWZ4SjGGYFdOBsn5Q4n1/view",
            "percent": 100,
            "hz": 240
        },
        {
            "user": "life is a game made for everyone",
            "link": "https://youtu.be/XbgcHTjy4Jw?si=LeVp0E55o3crAMRt&t=242",
            "percent": 100,
            "hz": 240
        }
    ]
}
